neuroqrs-0.1.4.dist-info/METADATA
neuroqrs-0.1.4.dist-info/WHEEL
neuroqrs/__init__.py
neuroqrs/genai.py
neuroqrs/index.py
neuroqrs/main.py
neuroqrs/utils.py
neuroqrs-0.1.4.dist-info/RECORD
