Metadata-Version: 2.1
Name: NeuroQRS
Version: 0.1.4
Summary: NeuroQRS (Neuro Query Recommendation System) is Faiss + LLM based query recommender with auto-improvement using closed feedback loop
Author-Email: Harishankar Kumar <hari01584@gmail.com>
License: MIT
Requires-Python: >=3.8
Requires-Dist: faiss-cpu>=1.7.4
Requires-Dist: sentence-transformers>=2.3.1
Requires-Dist: openai>=1.12.0
Requires-Dist: sphinx>=7.1.2
